aochallenge/__init__.py
aochallenge/__init__.pyi
aochallenge/debug.py
aochallenge/debug.pyi
aochallenge/grid.py
aochallenge/grid.pyi
aochallenge/image.py
aochallenge/image.pyi
aochallenge/input.py
aochallenge/input.pyi
aochallenge/py.typed
aochallenge/solver.py
aochallenge/solver.pyi
aochallenge-2.0.dist-info/METADATA
aochallenge-2.0.dist-info/WHEEL
aochallenge-2.0.dist-info/licenses/LICENSE
aochallenge-2.0.dist-info/RECORD
