Metadata-Version: 2.4
Name: aochallenge
Version: 2.0
Summary: A helper solution to speed up solving challenges like adventofcode
Project-URL: Homepage, https://github.com/fercsi/pylib-aochallenge
Project-URL: Bug Tracker, https://github.com/fercsi/pylib-aochallenge/issues
Author-email: Ferenc Vajda <ferenc.vajda@gmail.com>
License-File: LICENSE
Classifier: License :: OSI Approved :: MIT License
Classifier: Operating System :: OS Independent
Classifier: Programming Language :: Python :: 3
Requires-Python: >=3.11
